persistentdict/__init__.py
persistentdict/dict_in_redis.py
persistentdict-1.0.1.dist-info/LICENSE
persistentdict-1.0.1.dist-info/METADATA
persistentdict-1.0.1.dist-info/WHEEL
persistentdict-1.0.1.dist-info/top_level.txt
persistentdict-1.0.1.dist-info/RECORD
