Metadata-Version: 2.1
Name: persistentdict
Version: 1.0.1
Summary: Yet another dictionary backed by Redis DB
Home-page: https://github.com/user-cont/persistentdict
Author: Red Hat
Author-email: user-cont-team@redhat.com
License: MIT
Keywords: dict,durable,persistent,redis
Platform: UNKNOWN
Classifier: Environment :: Console
Classifier: Intended Audience :: Developers
Classifier: License :: OSI Approved :: MIT License
Classifier: Operating System :: POSIX :: Linux
Classifier: Programming Language :: Python
Classifier: Programming Language :: Python :: 3.6
Classifier: Programming Language :: Python :: 3.7
Classifier: Topic :: Software Development
Classifier: Topic :: Utilities
Requires-Python: >=3.6
Requires-Dist: redis
Provides-Extra: testing
Requires-Dist: pytest ; extra == 'testing'
